Workbook

Sheet DISCLOSURE
A1: PAE Portfolio Analytics — Spreadsheet Companion
A3: What this is
A4: A standalone educational companion to the PAE (Portfolio Analytics Engine) framework. It implements PAE's core analytics — risk metrics, factor attribution, scenario stress tests — as transparent spreadsheet formulas you can inspect, extend, and import into Google Sheets.
A6: NO ZERO-KNOWLEDGE ENCRYPTION — READ THIS FIRST
A7: Unlike the PAE application, this spreadsheet is NOT encrypted and provides NO zero-knowledge guarantees. Anything you type into this workbook (holdings, returns, notes) is stored in PLAIN TEXT inside this file. Do NOT enter passwords, account numbers, or any data you would not want readable by anyone who obtains this file.
A9: Educational analytics only
A10: This tool calculates; YOU decide. Nothing in this workbook is investment advice, and nothing here is a buy or sell recommendation. Past returns do not predict future results.
A12: Sample data is fictional
A13: All pre-filled holdings and returns are fictional SAMPLE data, clearly labeled as such. Replace them with your own figures before drawing any conclusions.
A15: Formula provenance
A16: Risk formulas implement engine/src/risk/metrics.rs. Stress shocks mirror engine/src/risk/stress.rs. The FACTORS sheet is a simplified attribution (exposure × factor return); the full OLS factor decomposition (betas, t-stats, R²) runs in the PAE Python engine at analytics/pae/models/factor.py.
A18: Regeneration
A19: Generated 2026-10-05 by tools/build_workbook.py (idempotent — safe to delete and regenerate at any time). Formulas use only Google-Sheets-compatible functions.

Sheet INPUT_Holdings
A1: Holdings — inputs (SAMPLE data)
A2: Amber cells are inputs. Replace the sample holdings with your own. Market Value is calculated (Quantity × Price).
A3: Symbol | B3: Asset Class | C3: Quantity | D3: Price (CAD) | E3: Market Value (CAD) | F3: Cost Basis (CAD) | G3: Yield %
A4: RY | B4: Equity | C4: 100 | D4: 150 | E4: =C4*D4 -> 15000 | F4: 12000 | G4: 0.038
A5: VCN | B5: Equity | C5: 200 | D5: 45 | E5: =C5*D5 -> 9000 | F5: 8000 | G5: 0.029
A6: XEF | B6: Equity | C6: 150 | D6: 38.5 | E6: =C6*D6 -> 5775 | F6: 5200 | G6: 0.027
A7: VAB | B7: Fixed Income | C7: 300 | D7: 26 | E7: =C7*D7 -> 7800 | F7: 8100 | G7: 0.034
A8: ZPR | B8: Preferred | C8: 250 | D8: 10.5 | E8: =C8*D8 -> 2625 | F8: 2800 | G8: 0.051
A9: CASH | B9: Cash | C9: 1 | D9: 12000 | E9: =C9*D9 -> 12000 | F9: 12000 | G9: 0.045
A10: VRE | B10: Real Estate | C10: 180 | D10: 22 | E10: =C10*D10 -> 3960 | F10: 3600 | G10: 0.042
A11: CGL.C | B11: Commodity | C11: 120 | D11: 28 | E11: =C11*D11 -> 3360 | F11: 3000 | G11: 0
A12: TOTAL | E12: =SUM(E4:E11) -> 59520 | F12: =SUM(F4:F11) -> 54700 | G12: =SUMPRODUCT(E4:E11,G4:G11)/E12 -> 0.035153226
A14: Note: asset-class names must match the SCENARIOS sheet exactly (Equity / Fixed Income / Commodity / Real Estate / Preferred / Cash).

Sheet RETURNS
A1: Monthly portfolio returns — SAMPLE data
A2: Fictional 24-month return series (Jan 2024 – Dec 2025). Columns D–G are calculation helpers for the RISK sheet. Replace column C with your own monthly returns.
A3: Mo | B3: Date | C3: Return | D3: Wealth index | E3: Running peak | F3: Drawdown | G3: Sorted returns
A4: 1 | B4: 2024-01 | C4: 0.021 | D4: =1*(1+C4) -> 1.021 | E4: =D4 -> 1.021 | F4: =IF(E4=0,0,(E4-D4)/E4) -> 0 | G4: =SMALL($C$4:$C$27,ROWS($G$4:G4)) -> -0.038
A5: 2 | B5: 2024-02 | C5: -0.014 | D5: =D4*(1+C5) -> 1.006706 | E5: =MAX(E4,D5) -> 1.021 | F5: =IF(E5=0,0,(E5-D5)/E5) -> 0.014 | G5: =SMALL($C$4:$C$27,ROWS($G$4:G5)) -> -0.031
A6: 3 | B6: 2024-03 | C6: 0.032 | D6: =D5*(1+C6) -> 1.0389206 | E6: =MAX(E5,D6) -> 1.0389206 | F6: =IF(E6=0,0,(E6-D6)/E6) -> 0 | G6: =SMALL($C$4:$C$27,ROWS($G$4:G6)) -> -0.027
A7: 4 | B7: 2024-04 | C7: 0.008 | D7: =D6*(1+C7) -> 1.047232 | E7: =MAX(E6,D7) -> 1.047232 | F7: =IF(E7=0,0,(E7-D7)/E7) -> 0 | G7: =SMALL($C$4:$C$27,ROWS($G$4:G7)) -> -0.021
A8: 5 | B8: 2024-05 | C8: -0.027 | D8: =D7*(1+C8) -> 1.0189567 | E8: =MAX(E7,D8) -> 1.047232 | F8: =IF(E8=0,0,(E8-D8)/E8) -> 0.027 | G8: =SMALL($C$4:$C$27,ROWS($G$4:G8)) -> -0.014
A9: 6 | B9: 2024-06 | C9: 0.015 | D9: =D8*(1+C9) -> 1.034241 | E9: =MAX(E8,D9) -> 1.047232 | F9: =IF(E9=0,0,(E9-D9)/E9) -> 0.012405 | G9: =SMALL($C$4:$C$27,ROWS($G$4:G9)) -> -0.012
A10: 7 | B10: 2024-07 | C10: 0.044 | D10: =D9*(1+C10) -> 1.0797477 | E10: =MAX(E9,D10) -> 1.0797477 | F10: =IF(E10=0,0,(E10-D10)/E10) -> 0 | G10: =SMALL($C$4:$C$27,ROWS($G$4:G10)) -> -0.009
A11: 8 | B11: 2024-08 | C11: -0.009 | D11: =D10*(1+C11) -> 1.0700299 | E11: =MAX(E10,D11) -> 1.0797477 | F11: =IF(E11=0,0,(E11-D11)/E11) -> 0.009 | G11: =SMALL($C$4:$C$27,ROWS($G$4:G11)) -> -0.005
A12: 9 | B12: 2024-09 | C12: 0.012 | D12: =D11*(1+C12) -> 1.0828703 | E12: =MAX(E11,D12) -> 1.0828703 | F12: =IF(E12=0,0,(E12-D12)/E12) -> 0 | G12: =SMALL($C$4:$C$27,ROWS($G$4:G12)) -> 0.007
A13: 10 | B13: 2024-10 | C13: -0.038 | D13: =D12*(1+C13) -> 1.0417212 | E13: =MAX(E12,D13) -> 1.0828703 | F13: =IF(E13=0,0,(E13-D13)/E13) -> 0.038 | G13: =SMALL($C$4:$C$27,ROWS($G$4:G13)) -> 0.008
A14: 11 | B14: 2024-11 | C14: 0.025 | D14: =D13*(1+C14) -> 1.0677642 | E14: =MAX(E13,D14) -> 1.0828703 | F14: =IF(E14=0,0,(E14-D14)/E14) -> 0.01395 | G14: =SMALL($C$4:$C$27,ROWS($G$4:G14)) -> 0.009
A15: 12 | B15: 2024-12 | C15: 0.018 | D15: =D14*(1+C15) -> 1.086984 | E15: =MAX(E14,D15) -> 1.086984 | F15: =IF(E15=0,0,(E15-D15)/E15) -> 0 | G15: =SMALL($C$4:$C$27,ROWS($G$4:G15)) -> 0.011
A16: 13 | B16: 2025-01 | C16: -0.012 | D16: =D15*(1+C16) -> 1.0739402 | E16: =MAX(E15,D16) -> 1.086984 | F16: =IF(E16=0,0,(E16-D16)/E16) -> 0.012 | G16: =SMALL($C$4:$C$27,ROWS($G$4:G16)) -> 0.012
... A27: 24 | B27: 2025-12 | C27: 0.014 | D27: =D26*(1+C27) -> 1.1710923 | E27: =MAX(E26,D27) -> 1.1710923 | F27: =IF(E27=0,0,(E27-D27)/E27) -> 0 | G27: =SMALL($C$4:$C$27,ROWS($G$4:G27)) -> 0.044
A29: Helpers: Wealth compounds (1+r). Peak is the running maximum of Wealth. Drawdown = (Peak − Wealth)/Peak. Sorted returns feed the rank-based VaR/CVaR (PAE engine definition: NOT interpolated).

Sheet RISK
A1: Risk metrics
A2: Implements engine/src/risk/metrics.rs as spreadsheet formulas over RETURNS!C4:C27. Sharpe/Sortino use the PAE engine definitions (monthly excess return over monthly volatility/downside deviation).
A3: Risk-free rate (annual) | B3: 0.04 | C3: Input cell for the risk-free rate.
A4: Metric | B4: Value | C4: Definition (PAE engine)
A5: Monthly volatility | B5: =STDEV(RETURNS!C4:C27) -> 0.021953838 | C5: STDEV.S equivalent — sample stdev (Bessel N−1), metrics.rs volatility()
A6: Annualized volatility | B6: =B5*SQRT(12) -> 0.076050327 | C6: Monthly vol × √12
A7: Mean monthly return | B7: =AVERAGE(RETURNS!C4:C27) -> 0.0068333333 | C7: Arithmetic mean of monthly returns
A8: Sharpe ratio | B8: =IF(B5=0,0,(B7-$B$3/12)/B5) -> 0.15942543 | C8: metrics.rs sharpe_ratio(): (mean − rf/12) / vol — monthly, NOT annualized
A9: Downside deviation | B9: =SQRT(SUMPRODUCT((RETURNS!C4:C27<$B$3/12)*(RETURNS!C4:C27-$B$3/12)^2)/COUNTIF(RETURNS!C4:C27,"<"&$B$3/12)) -> 0.025388372 | C9: RMS of (r − rf/12) over months BELOW rf/12 only — metrics.rs sortino_ratio()
A10: Sortino ratio | B10: =IF(COUNTIF(RETURNS!C4:C27,"<"&$B$3/12)=0,0,(B7-$B$3/12)/B9) -> 0.13785839 | C10: metrics.rs sortino_ratio(): (mean − rf/12) / downside dev; 0 if no downside months
A11: Max drawdown | B11: =MAX(RETURNS!F4:F27) -> 0.038 | C11: Largest peak-to-trough fall of the wealth index — metrics.rs max_drawdown()
A12: VaR 95% (monthly) | B12: =-INDEX(RETURNS!G4:G27,INT(0.05*COUNT(RETURNS!C4:C27))+1) -> 0.031 | C12: metrics.rs value_at_risk(): rank-based −sorted[⌊0.05·n⌋]; NOT the interpolated PERCENTILE — reported as positive loss
A13: CVaR 95% (monthly) | B13: =-AVERAGE(INDEX(RETURNS!G4:G27,2):INDEX(RETURNS!G4:G27,1+MAX(1,INT(0.05*COUNT(RETURNS!C4:C27))))) -> 0.038 | C13: metrics.rs conditional_var(): mean loss beyond the VaR rank, positive
A14: Total return (24 mo) | B14: =INDEX(RETURNS!D4:D27,COUNT(RETURNS!C4:C27))-1 -> 0.17109225 | C14: Compounded: ∏(1+r) − 1 — metrics.rs total_return()
A15: Annualized return | B15: =(1+B14)^(12/COUNT(RETURNS!C4:C27))-1 -> 0.082170159 | C15: (1+total)^(12/n) − 1 — metrics.rs annualized_return()

Sheet FACTORS
A1: Factor attribution (simplified)
A2: Contribution = exposure × factor return. Exposures and factor returns are MANUAL inputs (amber). The full OLS regression (betas, t-stats, R², variance decomposition) runs in the PAE Python engine: analytics/pae/models/factor.py.
A3: Factor | B3: Exposure β | C3: Factor return (annual) | D3: Contribution
A4: Market | B4: 0.95 | C4: 0.08 | D4: =B4*C4 -> 0.076
A5: Size | B5: 0.2 | C5: 0.02 | D5: =B5*C5 -> 0.004
A6: Value | B6: 0.35 | C6: 0.035 | D6: =B6*C6 -> 0.01225
A7: Momentum | B7: -0.1 | C7: 0.04 | D7: =B7*C7 -> -0.004
A8: Quality | B8: 0.25 | C8: 0.025 | D8: =B8*C8 -> 0.00625
A9: Alpha (manual residual) | B9: 0.005 | C9: — | D9: =B9 -> 0.005
A10: TOTAL explained | D10: =SUM(D4:D9) -> 0.0995
A12: Note: this is a top-down attribution, not the engine's variance decomposition. In analytics/pae/models/factor.py, each factor's contribution is β²·Var(factor)/Var(portfolio) from an OLS regression with intercept; residual risk = 1 − Σ contributions. With only 24 monthly observations the engine requires n ≥ k+2 (k = number of factors).

Sheet SCENARIOS
A1: Scenario stress tests
A2: Shock profiles mirror engine/src/risk/stress.rs (get_scenario_shocks). Allocation comes from INPUT_Holdings. Portfolio impact = Σ (allocation × shock). Shock cells are editable inputs (amber). Cash is modeled at 0% shock (the engine has no cash profile).
A3: Asset Class | B3: Allocation | C3: GFC 2008 | D3: COVID 2020 | E3: Rate shock
A4: Equity | B4: =SUMIF(INPUT_Holdings!$B$4:$B$11,$A4,INPUT_Holdings!$E$4:$E$11)/DASHBOARD!$B$4 -> 0.50025202 | C4: -0.5 | D4: -0.34 | E4: -0.25
A5: Fixed Income | B5: =SUMIF(INPUT_Holdings!$B$4:$B$11,$A5,INPUT_Holdings!$E$4:$E$11)/DASHBOARD!$B$4 -> 0.13104839 | C5: 0.05 | D5: 0.02 | E5: -0.15
A6: Commodity | B6: =SUMIF(INPUT_Holdings!$B$4:$B$11,$A6,INPUT_Holdings!$E$4:$E$11)/DASHBOARD!$B$4 -> 0.056451613 | C6: -0.35 | D6: -0.25 | E6: 0.1
A7: Real Estate | B7: =SUMIF(INPUT_Holdings!$B$4:$B$11,$A7,INPUT_Holdings!$E$4:$E$11)/DASHBOARD!$B$4 -> 0.066532258 | C7: -0.3 | D7: -0.15 | E7: -0.1
A8: Preferred | B8: =SUMIF(INPUT_Holdings!$B$4:$B$11,$A8,INPUT_Holdings!$E$4:$E$11)/DASHBOARD!$B$4 -> 0.044102823 | C8: -0.25 | D8: -0.2 | E8: -0.15
A9: Cash | B9: =SUMIF(INPUT_Holdings!$B$4:$B$11,$A9,INPUT_Holdings!$E$4:$E$11)/DASHBOARD!$B$4 -> 0.2016129 | C9: 0 | D9: 0 | E9: 0
A11: Scenario | B11: Portfolio impact | C11: Impact (CAD)
A12: GFC 2008 (2008-style) | B12: =SUMPRODUCT($B$4:$B$9,C$4:C$9) -> -0.29431704 | C12: =B12*DASHBOARD!$B$4 -> -17517.75
A13: COVID 2020 (2020-style) | B13: =SUMPRODUCT($B$4:$B$9,D$4:D$9) -> -0.20037802 | C13: =B13*DASHBOARD!$B$4 -> -11926.5
A14: Rate shock (2022-style) | B14: =SUMPRODUCT($B$4:$B$9,E$4:E$9) -> -0.15234375 | C14: =B14*DASHBOARD!$B$4 -> -9067.5
A16: Engine reference — stress.rs shocks: GFC 2008 equity −50% / fixed income +5%; COVID 2020 equity −34% / fixed income +2%; Rate shock 2022 equity −25% / fixed income −15% / commodity +10%. The engine's classify_asset() is a stub (all holdings → equity); this sheet maps each holding by its INPUT_Holdings asset class instead.

Sheet DASHBOARD
A1: Portfolio dashboard
A2: Summary cards pull live from the calculation sheets. Below: a plain-text interpretation guide (educational).
A3: Card | B3: Value | C3: Source
A4: NAV (CAD) | B4: =SUM(INPUT_Holdings!E4:E11) -> 59520 | C4: INPUT_Holdings
A5: Total cost basis (CAD) | B5: =SUM(INPUT_Holdings!F4:F11) -> 54700 | C5: INPUT_Holdings
A6: P&L (CAD) | B6: =B4-B5 -> 4820 | C6: This sheet
A7: P&L % | B7: =IF(B5=0,0,B6/B5) -> 0.088117002 | C7: This sheet
A8: Annualized volatility | B8: =RISK!B6 -> 0.076050327 | C8: RISK
A9: Sharpe ratio | B9: =RISK!B8 -> 0.15942543 | C9: RISK
A10: Sortino ratio | B10: =RISK!B10 -> 0.13785839 | C10: RISK
A11: Max drawdown | B11: =RISK!B11 -> 0.038 | C11: RISK
A12: VaR 95% (monthly) | B12: =RISK!B12 -> 0.031 | C12: RISK
A13: CVaR 95% (monthly) | B13: =RISK!B13 -> 0.038 | C13: RISK
A14: GFC 2008 impact | B14: =SCENARIOS!B12 -> -0.29431704 | C14: SCENARIOS
A15: COVID 2020 impact | B15: =SCENARIOS!B13 -> -0.20037802 | C15: SCENARIOS
A16: Rate shock impact | B16: =SCENARIOS!B14 -> -0.15234375 | C16: SCENARIOS
A19: Interpretation guide (educational)
A20: Metric | B20: What it means | C20: How to read it
A21: Volatility | B21: How much monthly returns typically wobble around their average. | C21: Higher = bumpier ride. Annualized ×√12 for comparability.
A22: Sharpe ratio | B22: Excess return per unit of total volatility (PAE engine: monthly). | C22: Above 1 is strong, below 0 means you trailed the risk-free rate.
A23: Sortino ratio | B23: Like Sharpe, but only downside wobbles count as risk. | C23: Higher = returns came with less painful downside.
A24: Max drawdown | B24: Worst peak-to-trough fall the portfolio suffered in the window. | C24: A 20% drawdown needs a 25% gain just to get back to even.
A25: VaR 95% | B25: On the 2nd-worst month out of 24, the loss was at most this. | C25: A planning number, not a worst case — tail losses exceed it.
A26: CVaR 95% | B26: Average loss in months worse than the VaR cutoff. | C26: More conservative than VaR; answers 'how bad is bad?'.
A27: Factor contribution | B27: How much of expected return each style factor explains. | C27: Simplified here; the engine estimates exposures by regression.
A28: Scenario impact | B28: What the portfolio would lose if a historical shock repeated. | C28: Shocks are stylized history, not forecasts.
A30: This tool calculates; you decide. Nothing here is investment advice or a buy/sell recommendation.
